{
    "swagger": "2.0",
    "info": {
        "contact": {}
    },
    "paths": {
        "/api/policies": {
            "get": {
                "description": "Get list of policies filtered by title, code, priority_level, created_after, created_before",
                "consumes": [
                    "application/json"
                ],
                "produces": [
                    "application/json"
                ],
                "tags": [
                    "policies"
                ],
                "summary": "List policies",
                "parameters": [
                    {
                        "type": "string",
                        "description": "Title contains",
                        "name": "title",
                        "in": "query"
                    },
                    {
                        "type": "string",
                        "description": "Policy code",
                        "name": "code",
                        "in": "query"
                    },
                    {
                        "type": "string",
                        "description": "Priority level",
                        "name": "priority_level",
                        "in": "query"
                    },
                    {
                        "type": "string",
                        "description": "Created after (RFC3339)",
                        "name": "created_after",
                        "in": "query"
                    },
                    {
                        "type": "string",
                        "description": "Created before (RFC3339)",
                        "name": "created_before",
                        "in": "query"
                    }
                ],
                "responses": {
                    "200": {
                        "description": "OK",
                        "schema": {
                            "type": "array",
                            "items": {
                                "$ref": "#/definitions/app.Policy"
                            }
                        }
                    },
                    "500": {
                        "description": "Internal Server Error",
                        "schema": {
                            "type": "object",
                            "additionalProperties": {
                                "type": "string"
                            }
                        }
                    }
                }
            }
        },
        "/api/policies/{id}": {
            "get": {
                "description": "Get detailed info for a policy by its ID",
                "consumes": [
                    "application/json"
                ],
                "produces": [
                    "application/json"
                ],
                "tags": [
                    "policies"
                ],
                "summary": "Get policy by ID",
                "parameters": [
                    {
                        "type": "string",
                        "description": "Policy ID",
                        "name": "id",
                        "in": "path",
                        "required": true
                    }
                ],
                "responses": {
                    "200": {
                        "description": "OK",
                        "schema": {
                            "$ref": "#/definitions/app.Policy"
                        }
                    },
                    "400": {
                        "description": "Bad Request",
                        "schema": {
                            "type": "object",
                            "additionalProperties": {
                                "type": "string"
                            }
                        }
                    },
                    "404": {
                        "description": "Not Found",
                        "schema": {
                            "type": "object",
                            "additionalProperties": {
                                "type": "string"
                            }
                        }
                    },
                    "500": {
                        "description": "Internal Server Error",
                        "schema": {
                            "type": "object",
                            "additionalProperties": {
                                "type": "string"
                            }
                        }
                    }
                }
            }
        }
    },
    "definitions": {
        "app.Policy": {
            "type": "object",
            "properties": {
                "alignment_nst": {
                    "type": "boolean"
                },
                "alignment_vision_2050": {
                    "type": "boolean"
                },
                "code": {
                    "type": "string"
                },
                "created_at": {
                    "type": "string"
                },
                "description": {
                    "type": "string"
                },
                "id": {
                    "type": "string"
                },
                "objectives": {
                    "description": "newline-separated",
                    "type": "string"
                },
                "priority_level": {
                    "type": "string"
                },
                "problem_statement": {
                    "type": "string"
                },
                "responsible_ministry": {
                    "type": "string"
                },
                "target_population": {
                    "type": "string"
                },
                "title": {
                    "type": "string"
                },
                "updated_at": {
                    "type": "string"
                }
            }
        }
    }
}